reader/__init__.py
reader/__main__.py
reader/config.txt
reader/feed.py
reader/viewer.py
alj_reader-1.0.0.dist-info/METADATA
alj_reader-1.0.0.dist-info/WHEEL
alj_reader-1.0.0.dist-info/entry_points.txt
alj_reader-1.0.0.dist-info/top_level.txt
alj_reader-1.0.0.dist-info/RECORD
