Metadata-Version: 2.2
Name: alj-reader
Version: 1.0.0
Summary: Read the latest Real Python tutorials
Home-page: https://github.com/realpython/reader
Author: Real Python
Author-email: ajackson54@shaw.ca
License: MIT
Classifier: License :: OSI Approved :: MIT License
Classifier: Programming Language :: Python :: 3
Classifier: Programming Language :: Python :: 3.7
Requires-Dist: feedparser
Requires-Dist: html2text
Dynamic: author
Dynamic: author-email
Dynamic: classifier
Dynamic: description
Dynamic: description-content-type
Dynamic: home-page
Dynamic: license
Dynamic: requires-dist
Dynamic: summary
